[
    {
        "ord": "0",
        "campus": "共同",
        "classes": "學生會",
        "name": "學生會",
        "content": "大家好，我們是111學年學生會，​\\n高科大原有建工與燕巢校區學生會、第一校區學生會、楠梓校區學生會、旗津校區學生會，分別管理各校區事務，因「大專院校學生會運作原則」規定，學校對外僅有一個學生會，故在將在111學年度正式合併，成為一個高科大學生會，負責統籌五校區活動、服務及事務。​\\n\\n「服務、奉獻、榮譽、創新、卓越」​​\\n\\n未來的學生會也將以五大精神，​\\n繼續服務高科大全體學生，\\n創造更好的高科生活，\\n已請大家繼續支持學生會，\\n讓學生會的服務遍佈在學生的周遭，\\n讓學生會的活動充實每個校區角落，\\n讓學生的權益真正的落實。\\n不論是學生會、社團或是學生，\\n也希望你我共同努力，\\n讓高科大更加優質。",
        "facebook": "https://www.facebook.com/%E5%9C%8B%E7%AB%8B%E9%AB%98%E9%9B%84%E7%A7%91%E6%8A%80%E5%A4%A7%E5%AD%B8-%E5%AD%B8%E7%94%9F%E6%9C%83-105100258936155",
        "instagram": "https://instagram.com/nkust_sa_111",
        "other": "https://nkustsa.webnode.tw/"
    },
    {
        "ord": "1",
        "campus": "第一",
        "classes": "系科",
        "name": "環境與安全衛生工程系學會",
        "content": "",
        "facebook": "",
        "instagram": "",
        "other": ""
    },
    {
        "ord": "2",
        "campus": "第一",
        "classes": "系科",
        "name": "機電工程系學會",
        "content": "",
        "facebook": "",
        "instagram": "",
        "other": ""
    },
    {
        "ord": "3",
        "campus": "第一",
        "classes": "系科",
        "name": "工業設計系學會",
        "content": "工業設計系原名為創新設計工程系，成立於2013年，2017年將原「機械與自動化工程系工業設計碩士班」整併為「創新設計工程系工業設計碩士班」，並自2019年8月1日起更名，現有師資 9 名，包含8名專任教師與1名專案教師，目前四技及研究所每年各招收一班，為一新興及小型規模之系所，但配合本系完善的設備與空間、人性化學習氛圍、產品設計及商品化設計快樂學習、超強設計實務及師資，致力於培養具有專業知識、工程技術與設計實務的產品設計人才，並結合創新思考及美學鑑賞能力，達到提昇本系產品設計在國內及國際上的競爭優勢。",
        "facebook": "",
        "instagram": "https://instagram.com/nkust_idesign?igshid=YmMyMTA2M2Y=",
        "other": ""
    },
    {
        "ord": "4",
        "campus": "第一",
        "classes": "系科",
        "name": "營建工程系學會",
        "content": "",
        "facebook": "",
        "instagram": "",
        "other": ""
    },
    {
        "ord": "5",
        "campus": "第一",
        "classes": "系科",
        "name": "電腦與通訊工程系學會",
        "content": "",
        "facebook": "",
        "instagram": "",
        "other": ""
    },
    {
        "ord": "6",
        "campus": "第一",
        "classes": "系科",
        "name": "電子工程系學會",
        "content": "",
        "facebook": "",
        "instagram": "",
        "other": ""
    },
    {
        "ord": "7",
        "campus": "第一",
        "classes": "系科",
        "name": "行銷與流通管理系學會",
        "content": "歡迎來到行銷系大家庭，各位如果碰上任何解決不了的問題，系學會都非常樂意幫忙（單身除外但歡迎各位來抱團取火）。 系上有許多活動像是迎新、聖誕小活動、萬聖趴、歌唱比賽和體育競賽等著各位。 你準備好充實大學生活了嗎？那就敬請期待吧！",
        "facebook": "http://www.md.nkfust.edu.tw/bin/home.php",
        "instagram": "http://www.md.nkust.edu.tw/",
        "other": ""
    },
    {
        "ord": "8",
        "campus": "第一",
        "classes": "系科",
        "name": "運籌管理系學會",
        "content": "",
        "facebook": "",
        "instagram": "",
        "other": ""
    },
    {
        "ord": "9",
        "campus": "第一",
        "classes": "系科",
        "name": "資訊管理系學會",
        "content": "資訊管理系(所)旨在培育敬業樂群、卓越創新、理論與實務並重的資管技術人員和資管經理人才，從事理論研究與實務應用的發展與推廣，以促進資訊科技在企業上的創新應用國家整體建設及地方發展。 具體而言，本系培養資管人才以市場需求為導向，並積極進行對產業界和社會的電子化服務，以及配合政府發展「智慧科技與電子商務」及「知識管理與科技運用」，和因應南部港灣地區工商業之快速發展。擁有產、官、學界豐富經驗的專任教師，教學經驗年資平均為二十年，相關教師實務經驗年資平均為五年。在學術上注重基本理論與學習能力的培養；在實務上注重工作實務與職場倫理的交流，落實理論與學習能力的培養。 我們擁有全國最好的設備與空間，如APP程式設計實驗室、雲端大數據實驗室以及智聯網創新應用實驗室，並導入整合型智慧科技學程、大數據分析學程以及跨領域人工智慧學程三大學程，提供學生高品質的教學課程與環境，接合產業趨勢發展。 資訊管理系有資訊管理碩士班以及電子商務碩士班。研究領域分為四大主軸，包括人工智慧和物聯網、金融科技和區塊鏈、電子商務和社群商務以及創新服務應用。碩士班教學研究成果豐碩，在全國兩大資管研討會中之教師及研究生論文發表皆名列前茅，科技部計劃及產學合作計劃亦表現亮麗。",
        "facebook": "https://www.facebook.com/groups/165920596801785/?ref=share_group_link",
        "instagram": "https://www.instagram.com/invites/contact/?i=2zrxjyq9esil&utm_content=2v69iup",
        "other": ""
    },
    {
        "ord": "10",
        "campus": "第一",
        "classes": "系科",
        "name": "風險管理與保險系學會",
        "content": "國立高雄科技大學師生規模為全國第二大，本系為南台灣唯一的風險管理與保險系所，設有海外雙聯學位選讀、赴姐妹校交換學習、VEE美國精算師證照科目抵免等，系所特色為: 　　一、 歷次教育部評鑑結果皆為一等，整體表現卓越。 　　二、 大學部、碩士班、碩士在職專班及博士班均備，學制完整。 　　三、 精算資訊與風險管理之整合規劃課程。 　　四、 實務專題製作與競賽。 　　五、 暑期及學期的校外實習。 　　六、 專業證照輔導如:美國產險核保CPCU、美國精算師檢定考試、產壽險核保理賠人員。 　　七、 優渥的專業及語言證照考照獎勵補助。",
        "facebook": "https://www.facebook.com/nkfustrmi/",
        "instagram": "https://instagram.com/nkust_27th_rmi?igshid=YmMyMTA2M2Y=",
        "other": ""
    },
    {
        "ord": "11",
        "campus": "第一",
        "classes": "系科",
        "name": "財務管理系學會",
        "content": "\"介紹：各位學弟妹你們好，首先恭喜你們加入了高科財管的大家庭。在此，僅代表系學會歡迎各位加入。有很多事情要跟你們介紹，但奈何篇幅問題，我們將會在新生始業的時候發放新生手冊，逐一跟你們介紹。有任何問題都可以透過以下聯絡資訊詢問:",
        "facebook": "",
        "instagram": "",
        "other": ""
    },
    {
        "ord": "財管系IG : nkust_finance",
        "campus": "",
        "classes": "",
        "name": "",
        "content": "",
        "facebook": "",
        "instagram": "",
        "other": ""
    },
    {
        "ord": "系會長IG :migger0906",
        "campus": "",
        "classes": "",
        "name": "",
        "content": "",
        "facebook": "",
        "instagram": "",
        "other": ""
    },
    {
        "ord": "Mail : c109126147@nkust.edu.tw",
        "campus": "",
        "classes": "",
        "name": "",
        "content": "",
        "facebook": "",
        "instagram": "",
        "other": ""
    },
    {
        "ord": "副會長IG : yeeling49",
        "campus": "",
        "classes": "",
        "name": "",
        "content": "",
        "facebook": "",
        "instagram": "",
        "other": ""
    },
    {
        "ord": "Mail : c109126119@nkust.edu.tw\"",
        "campus": "https://m.facebook.com/nkfustdepartmentoffinance/",
        "classes": "https://instagram.com/nkust_finance?igshid=YmMyMTA2M2Y=",
        "name": "",
        "content": "",
        "facebook": "",
        "instagram": "",
        "other": ""
    },
    {
        "ord": "12",
        "campus": "第一",
        "classes": "系科",
        "name": "金融系學會",
        "content": "本系主旨為以下五點: 1. 聯絡本系師生情誼。 2. 協助推廣學術研究及學術交流。 3. 進系內同學團結合作的精神。 4. 樹立良好的系風。 5. 培養自主管理精神為目的。 在人才培育上具有四項特色：創新教學、實務連結、專業發展與金融資訊。 並且在心態態度保持著積極卻不心急、踏實而不做作、努力但不放棄、追求不是強求",
        "facebook": "https://www.facebook.com/groups/769739147636935",
        "instagram": "https://instagram.com/nkust_first_dmb?r=nametag",
        "other": ""
    },
    {
        "ord": "13",
        "campus": "第一",
        "classes": "系科",
        "name": "應用英語系學會",
        "content": "哈囉各位新生們,歡迎加入應用英語系大家庭,系上會有許多課程可以選修,系上也會有許多活動可以參加,另外系上也有系隊可以自由參加,有籃球、羽球、男生排球和女生排球。",
        "facebook": "",
        "instagram": "https://www.instagram.com/ft_doe/",
        "other": ""
    },
    {
        "ord": "14",
        "campus": "第一",
        "classes": "系科",
        "name": "應用德語系學會",
        "content": "本系隸屬於高科大第一校區外語學院，四年課程以經貿實務之語言訓練為主，另外也包含德國歷史、文化等人文課程。此外，為了讓學生體驗德國文化，系上不僅提供了到德國交換的機會，也會舉辦與德國文化相關的活動，例如：啤酒節、文化體育週等，希望藉此激勵同學，共同進步。",
        "facebook": "https://m.facebook.com/Ifad.sa/?tsid=0.5272426929859746&source=result",
        "instagram": "https://instagram.com/ifad.nkust?igshid=YmMyMTA2M2Y=",
        "other": ""
    },
    {
        "ord": "15",
        "campus": "第一",
        "classes": "系科",
        "name": "應用日語系學會",
        "content": "",
        "facebook": "",
        "instagram": "",
        "other": ""
    },
    {
        "ord": "16",
        "campus": "第一",
        "classes": "學藝",
        "name": "火舞藝術表演社",
        "content": "初入大學的你，就如同等待綻放的火苗，在這裡，我們將會引領你認識肢體與火焰交織的美，加入火藝社，讓青春的舞台煥發著不一樣的光彩吧！",
        "facebook": "",
        "instagram": "https://instagram.com/nkust_k.f.a?igshid=YmMyMTA2M2Y=",
        "other": ""
    },
    {
        "ord": "17",
        "campus": "第一",
        "classes": "學藝",
        "name": "魔術社",
        "content": "大家好～我們是魔術社🎩✨ 社團成立是希望散播魔術的魅力，讓大家了解魔術的樂趣！(◍•ᴗ•◍) 每個禮拜都有2次社課，一次由專業指導老師教大家魔術，另一次由學長姐複習魔術&玩桌遊～也會辦社遊等促進社員間情誼的活動🤩 而且每學期末都會舉辦一次成發，可以在舞台上發光發熱😎🔥無論你是好奇魔術的奧秘，或單純想玩社團，都熱烈歡迎哦🥳👏🏻 快來加入我們吧⸜(๑⃙⃘'ᗜ'๑⃙⃘)⸝♡",
        "facebook": "https://www.facebook.com/NKUSTmagic/",
        "instagram": "https://www.instagram.com/nkust_magiclub/",
        "other": ""
    },
    {
        "ord": "18",
        "campus": "第一",
        "classes": "學藝",
        "name": "攝影社",
        "content": "歡迎加入攝影社！",
        "facebook": "https://www.facebook.com/snapfirst/",
        "instagram": "https://www.instagram.com/nkust_snap_first/",
        "other": ""
    },
    {
        "ord": "19",
        "campus": "第一",
        "classes": "學藝",
        "name": "益智桌上遊戲社",
        "content": "本社於民國102年創立，此時正是智慧型手機興盛的時期，手遊、社群媒體使人們交流的時間越來越少。創立宗旨希望大家以桌遊交朋友，開心聚在一起，重拾人與人之間的連結。",
        "facebook": "https://www.facebook.com/board.game.nkfust/?notif_id=1633548629307248&notif_t=page_user_activity&ref=notif",
        "instagram": "",
        "other": ""
    },
    {
        "ord": "20",
        "campus": "第一",
        "classes": "學藝",
        "name": "夢想漫研社",
        "content": "大家好~我們是夢想漫研社，這是一個你可以盡情地和ACGN同好們交流的地方。如果你想要提升繪畫技巧的話，我們有聘請校外的老師來教導繪畫漫畫的技巧歐!",
        "facebook": "https://www.facebook.com/NKUST.dcc",
        "instagram": "https://www.instagram.com/nkust.dcc/",
        "other": "https://twitter.com/dreamscomic8763"
    },
    {
        "ord": "21",
        "campus": "第一",
        "classes": "康樂",
        "name": "管樂社",
        "content": "我們由木管、銅管、打擊組成，在這裡只要有興趣，零基礎也可以加入！還有音樂會、比賽及社團活動可以一起玩樂並享受音樂的樂趣，歡迎熱愛音樂的你來加入管樂社！",
        "facebook": "https://m.facebook.com/NKFUSTWindBand/",
        "instagram": "https://instagram.com/nkfust_windband?igshid=YmMyMTA2M2Y=",
        "other": ""
    },
    {
        "ord": "22",
        "campus": "第一",
        "classes": "康樂",
        "name": "蔗園逸音國樂社",
        "content": "",
        "facebook": "",
        "instagram": "",
        "other": ""
    },
    {
        "ord": "23",
        "campus": "第一",
        "classes": "康樂",
        "name": "群音社",
        "content": "大家好我們是群音社！ 群音社跟其他音樂性社團差在哪呢？我們的樂器非常多元，除了一般表演的吉他、貝斯、鼓，還可以根據表演的歌來增加樂器層次，比如小提琴、大提琴，甚至是二胡、中國笛等等！而在曲風上也有更大的包容性，任何風格都能在群音表演！ 想學樂器、想表演、想唱歌的，就加入群音大家庭！",
        "facebook": "https://www.facebook.com/groups/215814458496669",
        "instagram": "https://www.instagram.com/gatheringmusicclub/",
        "other": ""
    },
    {
        "ord": "24",
        "campus": "第一",
        "classes": "康樂",
        "name": "阿卡貝拉社",
        "content": "安妞！我們是A CAPPELLA社。所謂Acappella是指不使用任何樂器，由純粹人聲所組成的「無樂器伴奏合唱團」。我們是由一群愛唱歌的大學生所組成，歡迎喜愛唱歌的您與我們一起挑戰人聲的極限。",
        "facebook": "https://www.facebook.com/nkustacappella",
        "instagram": "https://www.instagram.com/nkustacappella/",
        "other": "https://nkustacappella.github.io/"
    },
    {
        "ord": "25",
        "campus": "第一",
        "classes": "康樂",
        "name": "The Voicer 熱音社",
        "content": "The Voicer，譯為發聲者，是第一科大熱音社的家園，喜歡用熱血、用音樂詮釋一切情感， 我們在舞台上盡情宣洩，台下也熱烈呼應，如果你也喜歡各類曲風、喜歡與音樂為伍的朋友，期待你們成為The Voicer的一分子！",
        "facebook": "https://www.facebook.com/FranticFiveFightNKFUST/",
        "instagram": "https://instagram.com/nkust_thevoicer?igshid=YmMyMTA2M2Y=",
        "other": ""
    },
    {
        "ord": "26",
        "campus": "第一",
        "classes": "康樂",
        "name": "電子音樂文化社",
        "content": "高科大電子音樂文化社，是全台第一個在校園創立的電子音樂性質社團。 想了解派對文化又或者成為主宰派對氣氛的DJ嗎？高科電音社是由一群熱愛電子音樂的學生組成，時常舉辦大小型校內活動讓大家感受我們沸騰的血液。想學習要怎麼透過音樂引領活動嗎？或是與我們一起參加一場又一場的派對呢？歡迎加入高科電子音樂文化社！ 歡迎在星期四的晚上7:00~9:00，到第一校區活動中心的K202教室，跟我們一起玩～！！",
        "facebook": "https://www.facebook.com/electromusiccrew/",
        "instagram": "https://instagram.com/nkust_emc?igshid=YmMyMTA2M2Y=",
        "other": ""
    },
    {
        "ord": "27",
        "campus": "第一",
        "classes": "康樂",
        "name": "The one 吉他社",
        "content": "哈囉大家好我們是The One吉他社！吉他新手不知道去哪裡學？想表演卻沒有舞台？都歡迎你來吉他社和我們一起同樂！我們每周二、三晚上7:00-9:00在活動中心K401等你來玩！",
        "facebook": "",
        "instagram": "https://instagram.com/theoneguitar?igshid=YmMyMTA2M2Y=",
        "other": ""
    },
    {
        "ord": "28",
        "campus": "第一",
        "classes": "服務",
        "name": "懿馨社",
        "content": "「快樂地去完成，別人不想做的事」 你是不是對大學生活充滿嚮往呢！那就快來加入我們吧，喜歡小朋友的你不能錯過寒、暑營等活動的籌備，我們也有茶會、迎新…讓你能認識更多志同道合，一起當志工的好夥伴喔～",
        "facebook": "",
        "instagram": "https://instagram.com/nkust_sop?igshid=NmZiMzY2Mjc=",
        "other": ""
    },
    {
        "ord": "29",
        "campus": "第一",
        "classes": "服務",
        "name": "春暉社",
        "content": "各位小大一們大家好！我們春暉社是屬於服務性的社團，透過活動方式將春暉社宗旨「反菸、酒、毒、檳榔以及關懷愛滋。」傳遞給大家！ \\我們主要的活動有鬼屋、帶動中小學、以及聖誕營！ 喜愛參加活動的你/妳還在等什麼？趕快加入我們，與我們一起豐富大學生活吧！",
        "facebook": "國立高雄科技大學 - 第一校區春暉社 Sun Spring",
        "instagram": "nkustsunspring2.0",
        "other": ""
    },
    {
        "ord": "30",
        "campus": "第一",
        "classes": "服務",
        "name": "潛能領袖社",
        "content": "",
        "facebook": "",
        "instagram": "",
        "other": ""
    },
    {
        "ord": "31",
        "campus": "第一",
        "classes": "服務",
        "name": "扶輪青年社",
        "content": "",
        "facebook": "",
        "instagram": "",
        "other": ""
    },
    {
        "ord": "32",
        "campus": "第一",
        "classes": "服務",
        "name": "社福成長社",
        "content": "",
        "facebook": "",
        "instagram": "",
        "other": ""
    },
    {
        "ord": "33",
        "campus": "第一",
        "classes": "服務",
        "name": "動物保護社",
        "content": "我們支持TNR (誘捕、絕育、釋放Trap、Neuter、Release) 我們愛狗，不忍心讓牠們被抓進收容所後沒有人在乎，僅剩短短十二天的生命能夠存活。 不僅僅是狗，我們希望可以關心身邊可觸及的動物。 未來，也許，每種動物都可以擁有我們的愛以及完善的對待。",
        "facebook": "https://www.facebook.com/nkust.apc/",
        "instagram": "",
        "other": ""
    },
    {
        "ord": "34",
        "campus": "第一",
        "classes": "服務",
        "name": "高雄扶輪青年服務社",
        "content": "",
        "facebook": "",
        "instagram": "",
        "other": ""
    },
    {
        "ord": "35",
        "campus": "第一",
        "classes": "服務",
        "name": "唱詩分享社",
        "content": "",
        "facebook": "",
        "instagram": "",
        "other": ""
    },
    {
        "ord": "36",
        "campus": "第一",
        "classes": "服務",
        "name": "風險管理服務社",
        "content": "",
        "facebook": "",
        "instagram": "",
        "other": ""
    },
    {
        "ord": "37",
        "campus": "第一",
        "classes": "服務",
        "name": "崇德青年志工社",
        "content": "崇青社投入多類型的志工服務，寓教於樂。透過外在的付出，提升內涵，當自己心靈的志工。提倡環保蔬食、製作美味點心。崇青社讓你得到全方位的提升，充滿正能量及歡樂。",
        "facebook": "",
        "instagram": "https://www.instagram.com/cdyoung.de/?hl=zh-tw",
        "other": ""
    },
    {
        "ord": "38",
        "campus": "第一",
        "classes": "服務",
        "name": "佳音社",
        "content": "佳音社為一群基督徒學生組成的社團，喜歡探索基督信仰、學習彼此服務及關懷，並且將這樣的生活分享給高科大的師生，讓更多人認識福音！平常也會一起分享在生活中所面對的種種課題，以不同的想法互相交流，同時藉由禱告、讀聖經，認識基督教的世界觀，以學習如何在生活中實踐耶穌基督的愛，學習愛人、愛上帝，將這份愛傳揚出去。非常歡迎想來認識學長姊的同學以及有興趣想來認識基督信仰的人，讓我們一起享受美好的大學生活喔!!",
        "facebook": "",
        "instagram": "https://instagram.com/first_fellowship?igshid=YmMyMTA2M2Y=",
        "other": ""
    },
    {
        "ord": "39",
        "campus": "第一",
        "classes": "體能",
        "name": "羽球社",
        "content": "",
        "facebook": "",
        "instagram": "",
        "other": ""
    },
    {
        "ord": "40",
        "campus": "第一",
        "classes": "體能",
        "name": "熱舞社",
        "content": "",
        "facebook": "",
        "instagram": "",
        "other": ""
    },
    {
        "ord": "41",
        "campus": "第一",
        "classes": "體能",
        "name": "排球社",
        "content": "",
        "facebook": "",
        "instagram": "",
        "other": ""
    },
    {
        "ord": "42",
        "campus": "第一",
        "classes": "體能",
        "name": "柔道社",
        "content": "柔道社是一個運動性質社團，可以增強自己的體力及反應能力，也可以學習保護自己的能力，無論有沒有學習的經驗，都歡迎來柔道社體驗。",
        "facebook": "",
        "instagram": "https://www.instagram.com/judo_nkust/",
        "other": ""
    },
    {
        "ord": "43",
        "campus": "第一",
        "classes": "體能",
        "name": "悠游自在游泳社",
        "content": "",
        "facebook": "",
        "instagram": "",
        "other": ""
    },
    {
        "ord": "44",
        "campus": "第一",
        "classes": "體能",
        "name": "星野登山社",
        "content": "大家好！我們是星野登山社⛰️ 想爬大山無從入門？裝備昂貴難以負擔？想走中級山卻無人陪伴嗎？ 我們從零開始，教你在山上的食衣住行，陪你一同飽覽山的美！",
        "facebook": "https://www.facebook.com/nkuststarfield",
        "instagram": "https://www.instagram.com/nkust_starfield/",
        "other": ""
    },
    {
        "ord": "45",
        "campus": "第一",
        "classes": "體能",
        "name": "棒壘社",
        "content": "",
        "facebook": "",
        "instagram": "",
        "other": ""
    },
    {
        "ord": "46",
        "campus": "第一",
        "classes": "體能",
        "name": "桌球社",
        "content": "",
        "facebook": "",
        "instagram": "",
        "other": ""
    },
    {
        "ord": "47",
        "campus": "第一",
        "classes": "體能",
        "name": "網球社",
        "content": "本社團旨在讓每一位同學皆能了解網球這項運動，即使是零基礎的新手也沒有關係，會有教練及學長姊從旁教學，沒有球拍的同學也無須擔心，社團備有球拍供使用。",
        "facebook": "",
        "instagram": "https://www.instagram.com/nkust_no.1_tennisclub/",
        "other": ""
    },
    {
        "ord": "48",
        "campus": "第一",
        "classes": "聯誼",
        "name": "畢業生聯誼會",
        "content": "",
        "facebook": "",
        "instagram": "",
        "other": ""
    },
    {
        "ord": "50",
        "campus": "建工",
        "classes": "系科",
        "name": "模具工程系學會",
        "content": "",
        "facebook": "",
        "instagram": "",
        "other": ""
    },
    {
        "ord": "51",
        "campus": "建工",
        "classes": "系科",
        "name": "土木工程系學會",
        "content": "",
        "facebook": "",
        "instagram": "",
        "other": ""
    },
    {
        "ord": "52",
        "campus": "建工",
        "classes": "系科",
        "name": "機械工程系學會",
        "content": "我們是機械工程系學會，我們有優良傳統、有創新活動、還有熱心助人的幹部們，參加活動不僅豐富社交能力，更能跳脫平時課業的煩悶，希望大家能在大學生活留下精彩的回憶！",
        "facebook": "",
        "instagram": "https://www.instagram.com/nkust_me/",
        "other": ""
    },
    {
        "ord": "53",
        "campus": "建工",
        "classes": "系科",
        "name": "電子工程系學會",
        "content": "我們是一群，青春有活力的大學生，不管是在課業，還是辦活動我們都是全力以赴，我們也會比較常跟外系聯合辦活動，如果想更認識系內系外的弟弟妹妹們都可以多多參加我們舉辦的活動！",
        "facebook": "",
        "instagram": "https://instagram.com/nkust_110ec?igshid=YmMyMTA2M2Y=",
        "other": ""
    },
    {
        "ord": "54",
        "campus": "建工",
        "classes": "系科",
        "name": "電機工程系學會",
        "content": "",
        "facebook": "",
        "instagram": "",
        "other": ""
    },
    {
        "ord": "55",
        "campus": "建工",
        "classes": "系科",
        "name": "資訊工程系學會",
        "content": "",
        "facebook": "",
        "instagram": "",
        "other": ""
    },
    {
        "ord": "56",
        "campus": "建工",
        "classes": "系科",
        "name": "工業工程與管理系學會",
        "content": "",
        "facebook": "",
        "instagram": "",
        "other": ""
    },
    {
        "ord": "57",
        "campus": "建工",
        "classes": "系科",
        "name": "化學工程與材料工程系學會",
        "content": "",
        "facebook": "",
        "instagram": "",
        "other": ""
    },
    {
        "ord": "58",
        "campus": "建工",
        "classes": "系科",
        "name": "五專部模具工程科科學會",
        "content": "",
        "facebook": "",
        "instagram": "",
        "other": ""
    },
    {
        "ord": "59",
        "campus": "燕巢",
        "classes": "系科",
        "name": "人力資源發展系學會",
        "content": "",
        "facebook": "",
        "instagram": "",
        "other": ""
    },
    {
        "ord": "60",
        "campus": "燕巢",
        "classes": "系科",
        "name": "文化創意產業系學會",
        "content": "",
        "facebook": "",
        "instagram": "",
        "other": ""
    },
    {
        "ord": "61",
        "campus": "燕巢",
        "classes": "系科",
        "name": "會計資訊系學會",
        "content": "在未來的一年裡，我們將為各位準備豐富的活動：茶會、宿營、系烤、系尾牙、與外系聯合等各種活動，希望能讓各位熟悉校園，增進同儕間情誼，更快融入會資系這個大家庭。",
        "facebook": "",
        "instagram": "https://instagram.com/nkust_ai?igshid=YmMyMTA2M2Y=",
        "other": ""
    },
    {
        "ord": "62",
        "campus": "燕巢",
        "classes": "系科",
        "name": "金融資訊系學會",
        "content": "大家好，我們金融資訊系學會，系學會會在學期中舉辦許多大大小小不同的活動，除了自己系辦的制服日、抽直屬之外，還會與其他系一起合作活動，像是：宿營、聖誕舞會，有什麼問題都可以到系學會IG詢問，或是開學後直接到系辦找我們喔！",
        "facebook": "https://www.facebook.com/NKUST.FIN",
        "instagram": "https://instagram.com/nkust_fin?igshid=YmMyMTA2M2Y=",
        "other": ""
    },
    {
        "ord": "63",
        "campus": "燕巢",
        "classes": "系科",
        "name": "觀光管理系學會",
        "content": "大家好我們是111學年觀光管理系學會，將搭乘由我們帶領的飛船在這未知的宇宙中探索，找尋到自己的方向，為大學生活增添不一樣的樂趣。",
        "facebook": "",
        "instagram": "https://instagram.com/nkust_tma?igshid=YmMyMTA2M2Y=",
        "other": ""
    },
    {
        "ord": "64",
        "campus": "燕巢",
        "classes": "系科",
        "name": "智慧商務系學會",
        "content": "本系學會目的在於「服務系上」,不論是會員或是系上老師都是我們服務對象,與師長建立良好情感,舉辦活動促進會員之間交流,並做到監督學會之運作本分,讓資管系有家的感覺。 而我們也是系上對內對外的溝通橋樑,盡力協助會員及系上老師。 研究學術使會員有多方面的學習機會,發揚系譽展現系上應有特色。",
        "facebook": "",
        "instagram": "https://www.instagram.com/nkust_ic/",
        "other": "https://nkusticsa.wixsite.com/110th-ic"
    },
    {
        "ord": "65",
        "campus": "燕巢",
        "classes": "系科",
        "name": "財政稅務系學會",
        "content": "",
        "facebook": "",
        "instagram": "",
        "other": ""
    },
    {
        "ord": "66",
        "campus": "燕巢",
        "classes": "系科",
        "name": "國際企業系學會",
        "content": "",
        "facebook": "",
        "instagram": "",
        "other": ""
    },
    {
        "ord": "67",
        "campus": "燕巢",
        "classes": "系科",
        "name": "企業管理系學會",
        "content": "",
        "facebook": "",
        "instagram": "",
        "other": ""
    },
    {
        "ord": "69",
        "campus": "建工燕巢",
        "classes": "服務",
        "name": "WI-FI羅浮群",
        "content": "哈囉～大家好呀～我們是高科Wi－Fi羅浮群！ 有些人可能會好奇「羅浮」是什麼呢？？其實，「羅浮」也是童軍的一種哦！但是我們不會只有最基本的童軍技能學習，也融入了許多不同的元素，像是射箭、桌遊等等的課程，平時也會有像是露營、快閃表演、營隊等等各式各樣的活動可以參加，讓課程更加豐富有趣，也能夠在其中認識到來自不同地方的人們！ 在此誠摯的邀請大家加入我們高科Wi－Fi羅浮群，讓自己的大學生活更加精彩！ ❗社課時間會於開學後在IG粉專公佈，請大家密切關注！",
        "facebook": "https://www.facebook.com/NKUSTROVER",
        "instagram": "https://www.instagram.com/nkust_wifi_rovers/",
        "other": ""
    },
    {
        "ord": "70",
        "campus": "建工燕巢",
        "classes": "服務",
        "name": "慈濟大專青年社",
        "content": "",
        "facebook": "",
        "instagram": "",
        "other": ""
    },
    {
        "ord": "71",
        "campus": "建工燕巢",
        "classes": "學藝",
        "name": "映画社",
        "content": "社團課程內容包含學習電影藝術表演手法，電影史的解析以及其包含但意義，同時學習評論電影的各項特定及了解其代表的內涵與預表達之想法。",
        "facebook": "https://www.facebook.com/FilmClubNKUST/",
        "instagram": "https://instagram.com/filmclub_nkust?igshid=YmMyMTA2M2Y=",
        "other": ""
    },
    {
        "ord": "73",
        "campus": "建工燕巢",
        "classes": "學藝",
        "name": "翰林書法社",
        "content": "翰林書法社在高科大已成立四十九年之久，平日裡以書法藝術之研習為主，社課是在禮拜四的下午五點到七點，平日也可以自主練習，歡迎各位來加入書法社這個小家庭。",
        "facebook": "https://www.facebook.com/NKUSTCalligraphyClub/",
        "instagram": "https://www.instagram.com/110nkustcalligraphyclub/",
        "other": ""
    },
    {
        "ord": "74",
        "campus": "建工燕巢",
        "classes": "學藝",
        "name": "福智青年社",
        "content": "",
        "facebook": "",
        "instagram": "",
        "other": ""
    },
    {
        "ord": "75",
        "campus": "建工燕巢",
        "classes": "學藝",
        "name": "ACGN二次元研究社",
        "content": "我們社團旨在共同研究動畫與漫畫，遊戲與輕小說等文化，也有開繪圖的課程讓大家共同分享自己的創作，社團中還可以一起玩cosplay和出同人誌，我們繪圖有些人還擁有職業級的功力，歡迎喜歡二次元文化的大家加入我們。",
        "facebook": "https://www.facebook.com/nkustacgn",
        "instagram": "",
        "other": ""
    },
    {
        "ord": "76",
        "campus": "建工燕巢",
        "classes": "學藝",
        "name": "機車研究社",
        "content": "「轉下油門，遨遊這個世界」，旅程的重點不再於目的地，過程中的精采故事更耐人尋味，世界的美，需要你我親自尋覓。",
        "facebook": "https://m.facebook.com/NKUSTMTC/",
        "instagram": "https://www.instagram.com/nkust_mtc/",
        "other": ""
    },
    {
        "ord": "77",
        "campus": "建工燕巢",
        "classes": "學藝",
        "name": "籃球研究社",
        "content": "",
        "facebook": "",
        "instagram": "",
        "other": ""
    },
    {
        "ord": "78",
        "campus": "建工燕巢",
        "classes": "學藝",
        "name": "無人機研究社",
        "content": "",
        "facebook": "",
        "instagram": "",
        "other": ""
    },
    {
        "ord": "79",
        "campus": "建工燕巢",
        "classes": "學藝",
        "name": "多元議題研討社",
        "content": "關注各項多元議題並打造同溫層，目前最具專業資源的議題為多元性別，也希望讓身心障礙與各式議題被討論，望能藉本社讓各項學生需求被校方關注，讓同學們都能在學校快樂學習",
        "facebook": "",
        "instagram": "https://Instagram.com/cdis_nkust",
        "other": ""
    },
    {
        "ord": "80",
        "campus": "建工燕巢",
        "classes": "康樂",
        "name": "管樂社",
        "content": "管樂社於民國55年成立，在學校大力支持下持續追求創新與突破，朝向多元化發展。屢次於全國學生音樂比賽榮獲特優之佳績；社團不僅以樂會友、持續精進每個人的演奏技巧及專業能力，更能讓音樂生活化，深耕藝文發展。",
        "facebook": "https://www.facebook.com/NKUSTWindBand",
        "instagram": "https://instagram.com/nkust_wb_111?igshid=YmMyMTA2M2Y=",
        "other": ""
    },
    {
        "ord": "82",
        "campus": "建工燕巢",
        "classes": "康樂",
        "name": "攝影社",
        "content": "歷年來舉凡學校、社團，甚至外界舉辦的各種大小活動，無不由本社在活動中穿梭往來，一點一滴地仔細記錄，拍攝出精采之畫面，可說是一名默默付出的幕後英雄。 就如一句攝影名言：「捉住一瞬間，化一刻為永恆。」 因為學校有了這麼一個社團，讓更多有興趣的同學對攝影有進一步的了解，所以攝影社不但是學校的記錄者，更是攝影文藝風氣的宣傳者。",
        "facebook": "https://www.facebook.com/nkust.photoclub.fans/",
        "instagram": "https://www.instagram.com/110nkust.photographyclub/",
        "other": ""
    },
    {
        "ord": "83",
        "campus": "建工燕巢",
        "classes": "康樂",
        "name": "韻箏社",
        "content": "我們是因為熱愛古箏而相遇的一群人, 靈活的彈奏著對古箏熱情。 從傳統古箏曲到流行音樂,盡心盡力彈好每一個音符。 延續每一屆流傳下來的溫暖,屬於韻箏社的樂章, 永不歇息~",
        "facebook": "https://www.facebook.com/kuaszither/",
        "instagram": "https://www.instagram.com/nkustzitherclub/",
        "other": ""
    },
    {
        "ord": "84",
        "campus": "建工燕巢",
        "classes": "康樂",
        "name": "民謠吉他社",
        "content": "高科大-民謠吉他社，音樂性質的社團，時常舉辦成果發表以及名人講座、音樂競賽。每週都有社課能讓社員精進自己的能力，為每一次的表演做足準備。",
        "facebook": "https://www.facebook.com/kuasfolkguitar",
        "instagram": "https://www.instagram.com/nkust_fgc111/",
        "other": ""
    },
    {
        "ord": "85",
        "campus": "建工燕巢",
        "classes": "康樂",
        "name": "古典吉他社",
        "content": "\"由一群熱愛指彈吉他及古典吉他的人所組成的社團，純演奏不唱歌。",
        "facebook": "",
        "instagram": "",
        "other": ""
    },
    {
        "ord": "一、活動主旨： 透過社課，增加社員們古典吉他的技巧，以及培養與社員的感情，使社員間能夠互相交流和學習，使自身的琴藝能夠更上一層樓。",
        "campus": "",
        "classes": "",
        "name": "",
        "content": "",
        "facebook": "",
        "instagram": "",
        "other": ""
    },
    {
        "ord": "二、活動說明： 透過老師教學提升自身古典吉他技巧，老師會依據學生的程度進行分組，分為初階還有進階，初階的學生會學習較基礎的技巧例如撥弦以及按弦的技巧還有看譜的能力等等…而之前就學過有一些基礎的人就會被分配在進階班，進階班的學生會學習比較困難Fingerstyle技巧。 \"",
        "campus": "高科大-建工校區古典吉他社",
        "classes": "nkust_cgc",
        "name": "",
        "content": "",
        "facebook": "",
        "instagram": "",
        "other": ""
    },
    {
        "ord": "86",
        "campus": "建工燕巢",
        "classes": "康樂",
        "name": "典雅國樂社",
        "content": "大家好我們是典雅國樂社！ 只要對國樂有興趣，不管是從零開始學基礎或是有經驗的人都很歡迎～ 有興趣的同學來我們的期初迎新玩吧～有好聽好吃好玩的，也可以來我們IG粉專做更多詢問歐！",
        "facebook": "",
        "instagram": "https://instagram.com/nkust_cmc?igshid=YmMyMTA2M2Y=",
        "other": ""
    },
    {
        "ord": "87",
        "campus": "建工燕巢",
        "classes": "康樂",
        "name": "康樂輔導研習社",
        "content": "活力、自信、有效率、充滿朝氣的一群人 在無數的日子裡陪伴著...... 歡笑、汗水、淚水，交織成美好的片刻 想在大學生活裡留下熱血青春的回憶嗎？ 想擁有一群朝著相同目標衝的夥伴嗎？ 那就別猶豫加入康輔社就對啦！！！",
        "facebook": "https://www.facebook.com/KFStation/",
        "instagram": "https://instagram.com/nkustkfs42?r=nametag",
        "other": ""
    },
    {
        "ord": "88",
        "campus": "建工燕巢",
        "classes": "康樂",
        "name": "嘻哈文化研究社",
        "content": "高科嘻研歡迎所有喜歡嘻哈文化的朋友加入！不論是想要嘗試創作或是想在舞台上表演 都可以在社團得到很好的幫助，高科嘻研從創立到現在也參與了許多表演 有看過我們現場演出的朋友就能夠了解我們有多酷！",
        "facebook": "",
        "instagram": "https://instagram.com/nkusthiphop_official?igshid=YmMyMTA2M2Y=",
        "other": ""
    },
    {
        "ord": "89",
        "campus": "建工燕巢",
        "classes": "康樂",
        "name": "搖滾音樂社",
        "content": "搖滾音樂社起源於一些熱愛搖滾音樂的人。近年來喜愛搖滾音樂的學生想組團玩音樂。那天，熱愛搖滾音樂的同學決定在校園內尋找各方音樂好手，屬於搖滾音樂社的故事正式啟航。",
        "facebook": "https://www.facebook.com/KUAS.RockMusicCompany/",
        "instagram": "https://instagram.com/nkustrmc?igshid=YzAyZWRlMzg=",
        "other": ""
    },
    {
        "ord": "90",
        "campus": "建工燕巢",
        "classes": "體能",
        "name": "排球社",
        "content": "",
        "facebook": "",
        "instagram": "",
        "other": ""
    },
    {
        "ord": "92",
        "campus": "建工燕巢",
        "classes": "體能",
        "name": "羽球社",
        "content": "號外！號外！喜歡羽球的捧有們注意了，我們社團創立目的是為了提升同學們對羽球的熱愛，不管你是想來動一動開心打球還是想訓練更多羽球技巧，羽球社都歡迎你的加入喔！",
        "facebook": "",
        "instagram": "https://instagram.com/nkustbc111th?igshid=YmMyMTA2M2Y=",
        "other": ""
    },
    {
        "ord": "93",
        "campus": "建工燕巢",
        "classes": "體能",
        "name": "網球社",
        "content": "網球社是由一群熱愛網球運動的人所組成，希望藉由每一次舉辦不同的活動鼓勵社員一起來參加，並增加社員彼此之間情感，也讓大家在大學生活增添許多不同的樂趣與回憶。",
        "facebook": "https://www.facebook.com/kuastc/",
        "instagram": "https://www.instagram.com/ktc_family_nkust/",
        "other": ""
    },
    {
        "ord": "94",
        "campus": "建工燕巢",
        "classes": "體能",
        "name": "撞球社",
        "content": "各位剛生大一的學弟妹們，歡迎你們來高科這個大家庭，在精彩的大學生中，社團是不可獲缺的一部分，想必各位應該都有打過撞球吧？撞球是一個非常休閒好完的活動，如果對撞球有興趣的同學們，可以來撞球社跟其他的同學們一起切磋交流喔！社團還有教練會指導，有興趣的同學可以來喔！",
        "facebook": "",
        "instagram": "https://instagram.com/nkust_billiards?igshid=YmMyMTA2M2Y=",
        "other": ""
    },
    {
        "ord": "95",
        "campus": "建工燕巢",
        "classes": "體能",
        "name": "跑酷社",
        "content": "我們是愛運動的團體，有團體的活動，也有技術教學，喜歡運動的人，跑酷社會是你最棒的歸屬。",
        "facebook": "https://www.facebook.com/airfeetparkour",
        "instagram": "https://www.instagram.com/nkust_afp/",
        "other": ""
    },
    {
        "ord": "96",
        "campus": "建工燕巢",
        "classes": "體能",
        "name": "登山社",
        "content": "我們是高科大登山社（建工校區），美麗的高山草原，險峻的斷崖，每次旅程都伴隨不同成長，讓我們一同背起行囊向著山頭走去，用不同角度探索著這片土地，不管路多長多難走始終成為對方的動力。",
        "facebook": "",
        "instagram": "https://www.instagram.com/mtc_nkust/",
        "other": ""
    },
    {
        "ord": "97",
        "campus": "建工燕巢",
        "classes": "體能",
        "name": "滑板社",
        "content": "我們滑板社成立的宗旨是希望能讓更多人知道這個很酷的小眾文化，對你來說滑板是怎樣的存在呢？ 不管你是老手、新手、或是想嘗試看看的，都歡迎你加入高科滑板的大家庭！",
        "facebook": "",
        "instagram": "https://www.instagram.com/nkust_sbc/",
        "other": ""
    },
    {
        "ord": "98",
        "campus": "建工燕巢",
        "classes": "體能",
        "name": "水上活動社",
        "content": "水上活動社是一群愛玩水的人相聚的地方，舉辦有關水的活動，像是衝浪、潛水，知道很多隱藏景點可以去玩，歡迎喜歡玩水的伙伴加入我們的行列，一起去體驗許多有關水的活動吧~",
        "facebook": "https://www.facebook.com/kuasaacaac",
        "instagram": "https://www.instagram.com/nkust_aac/",
        "other": ""
    },
    {
        "ord": "99",
        "campus": "建工燕巢",
        "classes": "體能",
        "name": "街頭舞蹈社",
        "content": "凝聚校內喜愛跳舞的學生們，利用平日以及社團活動等時間彼此學習、交流、切磋，猶如一個大家庭，我們的舞風有Hip hop、Locking、Popping、Dancehall、Jazz、Breaking，歡迎喜愛舞蹈的同學都可以來加入我們街頭舞蹈社。",
        "facebook": "",
        "instagram": "https://instagram.com/indc_nkuststreetdance?igshid=NmZiMzY2Mjc=",
        "other": ""
    },
    {
        "ord": "100",
        "campus": "建工燕巢",
        "classes": "體能",
        "name": "爵士有氧社",
        "content": "我們聚集一群熱愛運動、挑戰的朋友，以認真的心去面對每一個事物，相互扶持，累積有關體適能、各類有氧運動、瑜珈及 ZUMBA 等知識和技能，揮灑對生命的熱情，期待大家從我們的努力中感受運動對生活的重要。",
        "facebook": "",
        "instagram": "https://www.instagram.com/nkust_jac/",
        "other": ""
    },
    {
        "ord": "101",
        "campus": "建工燕巢",
        "classes": "體能",
        "name": "中華武術社",
        "content": "",
        "facebook": "",
        "instagram": "",
        "other": ""
    },
    {
        "ord": "102",
        "campus": "建工燕巢",
        "classes": "體能",
        "name": "跆拳道社",
        "content": "",
        "facebook": "",
        "instagram": "",
        "other": ""
    },
    {
        "ord": "103",
        "campus": "建工燕巢",
        "classes": "體能",
        "name": "棒球社",
        "content": "我們就像是一個大家庭，團結、互助、一起奮鬥，堅持到底，不輕言放棄這是我們的態度，加入我們，與我們一同突破自我。",
        "facebook": "https://www.facebook.com/kuasbaseballclub/",
        "instagram": "https://instagram.com/nkust_kbc?igshid=YmMyMTA2M2Y=",
        "other": ""
    },
    {
        "ord": "104",
        "campus": "建工燕巢",
        "classes": "體能",
        "name": "足球隊",
        "content": "我們是高科大足球隊，由一群熱愛踢足球的學生們組成。練習時間為每週二、四晚上及每週六下午，歡迎對足球有熱忱且熱愛團隊運動的新生們加入足球隊大家庭！",
        "facebook": "",
        "instagram": "https://instagram.com/nkustfootball?r=nametag",
        "other": ""
    },
    {
        "ord": "105",
        "campus": "楠梓",
        "classes": "系科",
        "name": "半導體工程系學會",
        "content": "主要培育半導體製程、系統應用設計及測試的專業人才，配合我國尖端的半導體產業人力需求，以提升我國IC產業的產品產量及品質，並加應用面拓展至生醫光電、鐵道機電整合、監控與AIOT。",
        "facebook": "",
        "instagram": "https://www.instagram.com/nkust.mee/",
        "other": ""
    },
    {
        "ord": "106",
        "campus": "楠梓",
        "classes": "系科",
        "name": "造船及海洋工程系學會",
        "content": "大家好我們是高雄科技大學的造船與海洋工程系，本科系是一門融合了船舶、海洋結構、機械、電機、等等各種理論與技術的工程科系。每年都有很多多元創新的活動歡迎大家參與。",
        "facebook": "",
        "instagram": "https://www.instagram.com/nkust_dnaoe/",
        "other": "https://dnaoe.nkust.edu.tw/"
    },
    {
        "ord": "107",
        "campus": "楠梓",
        "classes": "系科",
        "name": "電訊工程系學會",
        "content": "本系在未來的發展上將涵蓋行動通訊 ，船舶通訊，衛星通訊及衛星導航等陸、海、空通訊領域，並積極與電腦相結合，朝新型數位通訊的領域發展而努力。為配合我國電子通訊相關產業之發展方向與目標，將系教學與研究主體以電子通訊相關技術為主軸，配合海洋科技大學特色，發展與海洋電訊工程應用相關之研究。",
        "facebook": "",
        "instagram": "https://www.instagram.com/nkusttesa/",
        "other": "https://ece.nkust.edu.tw"
    },
    {
        "ord": "108",
        "campus": "楠梓",
        "classes": "系科",
        "name": "漁業生產與管理系學會",
        "content": "",
        "facebook": "",
        "instagram": "",
        "other": ""
    },
    {
        "ord": "109",
        "campus": "楠梓",
        "classes": "系科",
        "name": "水產食品科學系學會",
        "content": "本系課程係以水產食品為基礎，並培養學生食品加工、衛生安全檢驗、食品生物技術等相關技術，亦設計多元的選修課程提供學生修習，以培養食品加工、研究開發、品管檢驗等專業人才。",
        "facebook": "https://m.facebook.com/nkustdsfs",
        "instagram": "https://instagram.com/nkust_dsfs?igshid=YmMyMTA2M2Y=",
        "other": "https://dsfs.nkust.edu.tw/"
    },
    {
        "ord": "110",
        "campus": "楠梓",
        "classes": "系科",
        "name": "水產養殖系學會",
        "content": "系學會由本系學生組成，為辦理水產養殖系上活動與協助水產養殖系師生的自治性組織，每學年皆會辦理新生茶會、迎新、公益週、養殖盃球類競賽、系週會，並與水圈學院其他系學會舉辦水圈盃球類競賽，水圈金頭腦問答比賽，與全校聯合舉辦制服日等活動，加入系學會成員可與其他成員共同舉辦活動，學習並實踐領導、文書處理，活動設計等 系主任擔任指導老師，三年級學生擔任會長、副會長，以及其他自願學生擔任幹部，系會位於系館樂群樓一樓面西(面向停車場)的左手邊",
        "facebook": "https://www.instagram.com/nkust_aqua/",
        "instagram": "https://reurl.cc/GEmROZ",
        "other": ""
    },
    {
        "ord": "111",
        "campus": "楠梓",
        "classes": "系科",
        "name": "海洋生物技術系學會",
        "content": "",
        "facebook": "",
        "instagram": "",
        "other": ""
    },
    {
        "ord": "112",
        "campus": "楠梓",
        "classes": "系科",
        "name": "海洋環境工程系學會",
        "content": "\"歡迎來到海洋環境工程系學會",
        "facebook": "",
        "instagram": "",
        "other": ""
    },
    {
        "ord": "系學會成立的主旨在於替系上籌畫許多活動，包含每個新生最期待的迎新、眾多人喜愛的歌唱大賽、還有拉近系上師生關係、能點燃系上熱情的運動球賽、以及與學長姐拉近彼此關係的各項活動包括。",
        "campus": "",
        "classes": "",
        "name": "",
        "content": "",
        "facebook": "",
        "instagram": "",
        "other": ""
    },
    {
        "ord": "這些活動，不只是為了拓展更高更廣的視野，更是為了培育大學生為眾人服務的精神與態度，學習成為一個以服務為本的系會成員，因為這些每年都會舉辦的活動，我們維繫了系上同學們的感情、增進了與老師們的互動，同時也培養了個人與團隊的合作精神，並讓參與系學會的成員學習如何有效管理、善用溝通技巧， 並藉由參與系會，引領自己發揮個人特質，體驗追逐夢想時所留下的汗水，進而從中獲得成就與自我肯定。\"",
        "campus": "",
        "classes": "https://www.instagram.com/nkust_meesa/",
        "name": "nkustmee.nkust.edu.tw/?aid=401",
        "content": "",
        "facebook": "",
        "instagram": "",
        "other": ""
    },
    {
        "ord": "113",
        "campus": "楠梓",
        "classes": "系科",
        "name": "航運管理系學會",
        "content": "本系教育目標在培育專業、敬業、樂群的航運物流相關事業之經營管理與實務人才，藉以提昇國內海運、空運與國際物流等專業管理技術，增加國家的國際競爭力。研究所則以海運、空運與國際物流管理等三大領域為主。在課程安排上大學部以實務教學為主，共分為海運管理、空運管理、國際物流管理、資訊科技、外語與一般基礎管理等系列",
        "facebook": "https://www.facebook.com/nkuststm/",
        "instagram": "https://www.instagram.com/nkust.stm/",
        "other": "http://www.stm.nkmu.edu.tw/"
    },
    {
        "ord": "114",
        "campus": "楠梓",
        "classes": "系科",
        "name": "商務資訊應用系學會",
        "content": "培育貼近業界趨勢與市場需求的資訊專業人才，並兼具商業管理知能，有別於他校資管系，除了訓練學生之資訊專業知識與實務技能外，同時加強海事相關產業所需的資訊管理能力。",
        "facebook": "https://www.facebook.com/nkustbc/",
        "instagram": "",
        "other": "http://mis.nkmu.edu.tw"
    },
    {
        "ord": "115",
        "campus": "楠梓",
        "classes": "系科",
        "name": "供應鏈管理系學會",
        "content": "協助台灣傳統產業的供應鏈發展與管理，並強調跨組織合作、與海洋特色，發展水產品供應鏈、綠色供應鏈及緊急運籌。",
        "facebook": "",
        "instagram": "https://www.instagram.com/nkust_scm/",
        "other": "http://scm.nkust.edu.tw"
    },
    {
        "ord": "116",
        "campus": "楠梓",
        "classes": "系科",
        "name": "海洋休閒管理系學會",
        "content": "具備基本海洋知識、認識海洋生態環境、培養水域活動專業及管理人才、熟悉水域活動器材之操作以及了解如何判斷水域活動範圍之安全。除了有以上管理相關專業課程還有術科方面，例如潛水、組船開船以及學習其他水上設施，為了讓學生能夠更加的熟悉各方面的領域。",
        "facebook": "https://www.facebook.com/dasmnkmu",
        "instagram": "https://instagram.com/nkust_dmlmsa?igshid=YmMyMTA2M2Y=",
        "other": "http://www.dmlm.nkust.edu.tw"
    },
    {
        "ord": "117",
        "campus": "楠梓",
        "classes": "康樂",
        "name": "管樂社",
        "content": "管樂社是一個活潑的社團，我們會參加各式各樣的表演以及全國學生音樂比賽，我們也會跟其他校區的管樂社交流切磋，如果你學生時期的最後，還抱有對音樂的熱情，都歡迎加入管樂社這個大家庭，讓我們一起用音樂寫下燦爛的大學生活。",
        "facebook": "https://www.facebook.com/NKMUwindband/",
        "instagram": "https://reurl.cc/b20YVd",
        "other": ""
    },
    {
        "ord": "118",
        "campus": "楠梓",
        "classes": "康樂",
        "name": "民謠吉他社",
        "content": "民謠吉他社是一群熱愛音樂的學生組合起來的大家庭，課堂當中即便是零基礎的學生，我們也都會安排基礎課程，在每學期期末也會安排成果發表會，讓大家在舞台上發光發熱。就讓對音樂充滿熱忱的自己，加入我們這個歡樂的大家庭，讓自己大學青春留下美好的回憶吧！",
        "facebook": "",
        "instagram": "https://www.instagram.com/nkust_guitar/",
        "other": ""
    },
    {
        "ord": "119",
        "campus": "楠梓",
        "classes": "康樂",
        "name": "古箏社",
        "content": "當古裝劇主角在彈奏古箏時，你是否有股衝動想與他一同演奏呢？無論是衝動還是心動請你馬上行動！你還在等什麼？下一個古裝劇主角就是你！古箏可以長遠悠揚，更可以氣勢磅礡，歡迎對古箏有興趣有熱忱的你加入",
        "facebook": "https://www.facebook.com/NKMUguzheng/",
        "instagram": "https://www.instagram.com/nkust_guzheng/",
        "other": ""
    },
    {
        "ord": "120",
        "campus": "楠梓",
        "classes": "康樂",
        "name": "搖滾音樂社",
        "content": "你是充滿青春熱血的人嗎？想來學樂器、玩樂團、交朋友，並在大學留下美好的回憶嗎？那麼請你加入搖音社，跟我們一起玩社團！！",
        "facebook": "https://www.facebook.com/nkustRMC/",
        "instagram": "https://www.instagram.com/nkust_rmc/",
        "other": ""
    },
    {
        "ord": "121",
        "campus": "楠梓",
        "classes": "康樂",
        "name": "熱門舞蹈社",
        "content": "給愛跳舞及對舞台有憧憬的你！這裡是NTDC，我們舞風多變，可以很帥，也可以很美，不管有沒有基礎，只要你喜歡跳舞、嚮往舞台，NTDC就是你最好的選擇。歡迎加入熱舞社這個大家庭！",
        "facebook": "",
        "instagram": "https://www.instagram.com/nkustntdc/",
        "other": ""
    },
    {
        "ord": "122",
        "campus": "楠梓",
        "classes": "康樂",
        "name": "搞怪魔術社",
        "content": "是不是看到魔術師變魔術會對這背後的祕密感到很好奇?想知道嗎?想學嗎?歡迎加入搞怪魔術社，一起開心的學魔術吧!",
        "facebook": "https://www.facebook.com/NKUSTmagic",
        "instagram": "https://www.instagram.com/nkust_magiclub/",
        "other": ""
    },
    {
        "ord": "123",
        "campus": "楠梓",
        "classes": "康樂",
        "name": "嘻哈音樂研究社",
        "content": "",
        "facebook": "",
        "instagram": "",
        "other": ""
    },
    {
        "ord": "124",
        "campus": "楠梓",
        "classes": "康樂",
        "name": "MV舞蹈社",
        "content": "我們MV舞蹈社是以學習KPOP舞蹈為主的社團，在這裡你可以依照自己的喜好來選擇你想學的MV舞蹈，並認識更多喜歡韓流文化的親故們！當然在學期中會舉辦有關韓國文化的活動，也有許多表演的機會喔！不管你是愛Kpop愛跳舞，還是擁有熱情的表演魂，都可以來加入我們！快來跟我們一起開心跳舞吧！",
        "facebook": "",
        "instagram": "https://instagram.com/nkust_mv_dance?igshid=YmMyMTA2M2Y=",
        "other": ""
    },
    {
        "ord": "125",
        "campus": "楠梓",
        "classes": "服務",
        "name": "登峰無限社",
        "content": "「我們真的不是登山社啦」，我們是以基督教信仰為核心價值，以協助學生探索無限潛能、建立品格生命、開創登峰造極人生。本社備有輕鬆、友善、無壓力的歡樂社課，社課會安排「領導力訓練」、「戀愛課程」、「職涯規劃」等主題，希望幫助學生更認識自己，並具備未來社會需求－領導力、團隊合作能力、溝通能力、解決問題能力、時間管理能力等「軟實力」，還有讓你放鬆身心或瘋狂動腦的「桌遊趴」！我們固定每週二社課，提供免費晚餐。",
        "facebook": "https://www.facebook.com/NKMU.DengFong/",
        "instagram": "",
        "other": ""
    },
    {
        "ord": "126",
        "campus": "楠梓",
        "classes": "服務",
        "name": "全人領袖社",
        "content": "全人領袖社為服務性社團，我們跟楠梓區多所國中小進行合作，實際進入到國中小內部進行生命品格教育，也在寒暑假期間舉辦冬夏令營，周六也會有專為兒童所舉辦的志工活動，免費才藝班等。",
        "facebook": "https://www.facebook.com/SuperLeaderClub/",
        "instagram": "https://reurl.cc/o1WymQ",
        "other": ""
    },
    {
        "ord": "127",
        "campus": "楠梓",
        "classes": "服務",
        "name": "中智佛學社",
        "content": "學習佛法的最終目的是為了從輪迴中解脫，使生命不再受煩惱、苦痛所困。我們如果能循著佛陀的腳步，學會其中的道理並善用在生活中，也能使我們離苦得樂，人生更加幸福。每週四中午花一點時間，享用蔬食、聽法學習。",
        "facebook": "https://www.facebook.com/groups/1066351803384425",
        "instagram": "https://www.instagram.com/nkustzz/",
        "other": ""
    },
    {
        "ord": "128",
        "campus": "楠梓",
        "classes": "服務",
        "name": "崇德青年志工社",
        "content": "本社團抱著服務的熱忱，上山下海、關懷弱勢團體、兒童品格教育的帶動…，以及和各校的志工伙伴互相交流，參與志工研習、心靈成長營等活動，從中更加了解自己，並學習將服務的精神落實於日常生活中。在校會舉辦各類活動，如廚藝交流、點心製作、手工藝教學等，推動環保蔬食。",
        "facebook": "",
        "instagram": "",
        "other": ""
    },
    {
        "ord": "129",
        "campus": "楠梓",
        "classes": "學藝",
        "name": "漫畫研究社",
        "content": "本社團提供本校動漫畫愛好者之交流研習場所，提倡動漫畫藝術之研習及創作風氣，傳播動漫畫藝術之相關知識，並藉此提升本校藝術 素養，促進本土動漫界之發展。",
        "facebook": "https://www.facebook.com/NKUSTKMCC/",
        "instagram": "https://www.instagram.com/nkust_acg/",
        "other": ""
    },
    {
        "ord": "130",
        "campus": "楠梓",
        "classes": "學藝",
        "name": "烘培社",
        "content": "烘培社一直是超級熱門的社團！因為有名額限制，一直非常搶手😖我們除了動手做出各式各樣的甜點，還有很多社員福利活動✨✨歡迎參考我們的粉專，持續追蹤最新消息🔔歡迎加入我們🙋🏻‍♀️一起變成厲害的糕點師吧👩‍🍳💗",
        "facebook": "https://www.facebook.com/nkustbakingclub/",
        "instagram": "https://www.instagram.com/nkust_bakingclub/",
        "other": ""
    },
    {
        "ord": "131",
        "campus": "楠梓",
        "classes": "學藝",
        "name": "海洋文化社",
        "content": "",
        "facebook": "",
        "instagram": "",
        "other": ""
    },
    {
        "ord": "132",
        "campus": "楠梓",
        "classes": "學藝",
        "name": "飆光舞蹈藝術社",
        "content": "",
        "facebook": "",
        "instagram": "",
        "other": ""
    },
    {
        "ord": "133",
        "campus": "楠梓",
        "classes": "體能",
        "name": "海羽羽球社",
        "content": "海羽羽球社是一個充滿溫暖快樂氣息的地方，每個人都因爲打球認識彼此，歡迎加入這個大家庭",
        "facebook": "https://www.facebook.com/sbcnkust/",
        "instagram": "https://www.instagram.com/sbc_nkust/",
        "other": ""
    },
    {
        "ord": "134",
        "campus": "楠梓",
        "classes": "體能",
        "name": "深藍社",
        "content": "深藍社主要從事的活動為滑板、衝浪及水肺潛水，在課程中也會聘請專業且優秀的教練為大家上課，除了上述的水域活動之外，愛護海洋環境也是我們的宗旨之一，定期的淨灘也是我們常會舉辦的活動，所以如果你熱愛海洋也想和我們一起保護地球的話，深藍社絕對是你的第一選擇！快來加入深藍社讓我們一起感受大海的魅力吧！",
        "facebook": "",
        "instagram": "https://www.instagram.com/divingblue_nkust/",
        "other": ""
    },
    {
        "ord": "135",
        "campus": "楠梓",
        "classes": "體能",
        "name": "科學武術社",
        "content": "科武防身系統將武術系統重新整理，將一般常發生狀況歸納，把所有的教學都鎮定在能讓學員了解動作如何操作、什麼時侯操作、為什麼這麼操作，不同情況分別要有什麼應對觀念。所以學習科武能非常省時有效率、不需要特別刻苦耐勞、排除體格身材性別與年齡的弱勢。我們都不知道危險在什麼時候會來，所以要做好準備！",
        "facebook": "",
        "instagram": "",
        "other": ""
    },
    {
        "ord": "136",
        "campus": "楠梓",
        "classes": "其他",
        "name": "親善大使團",
        "content": "楠梓校區親善大使團是以服務群眾為目的成立的社團，在本校的重要活動或是校外貴賓來訪時，負責出勤接待以及引導，團隊會定期辦理彩妝、美姿美儀、體態雕塑、團隊溝通等專業課程，在這些課程中更精進自己，並透過出勤累積服務經驗，用我們最真誠的微笑，獻上最專業的服務。",
        "facebook": "https://reurl.cc/Wrlx5O",
        "instagram": "https://www.instagram.com/nkust_goodwill_ambassador/",
        "other": ""
    },
    {
        "ord": "137",
        "campus": "楠梓",
        "classes": "其他",
        "name": "競技啦啦隊",
        "content": "哈囉大家！我們是競技啦啦隊！想要呼吸上層的新鮮空氣，體驗在高空中飛的感覺嗎？想要增肌減脂、鍛鍊肌肉，讓自己擁有更良好的體態嗎？還是想要挑戰自己，像體操選手一樣翻騰飛躍呢？！！不用擔心自己沒有基礎、平時不會運動、身材體態不佳或是不會跳舞，完全沒有限制！！零基礎開始學習，只要你/妳肯努力，我們找的就是你/妳！「青春、熱血、活力，讓我們一起創造不一樣的回憶。」Go sharks！！",
        "facebook": "https://reurl.cc/QLzEeo",
        "instagram": "https://www.instagram.com/nkust_sharkscheerleading/",
        "other": ""
    },
    {
        "ord": "138",
        "campus": "楠梓",
        "classes": "其他",
        "name": "高科生力軍",
        "content": "高科大最閃耀的代言人，結合五大校區，不僅可以認識許多外系外校的朋友，更重要的是，只要生力軍在手，上台簡報能力絕對有！吃喝玩樂不可少，團遊、野餐、聖誕趴樣樣齊全，大學第一步，就從生力軍開始吧！",
        "facebook": "https://www.facebook.com/guidenkust",
        "instagram": "https://www.instagram.com/guide_nkust",
        "other": ""
    },
    {
        "ord": "139",
        "campus": "旗津",
        "classes": "系科",
        "name": "航運技術系學會",
        "content": "",
        "facebook": "",
        "instagram": "",
        "other": ""
    },
    {
        "ord": "140",
        "campus": "旗津",
        "classes": "系科",
        "name": "輪機工程系學會",
        "content": "",
        "facebook": "",
        "instagram": "",
        "other": ""
    },
    {
        "ord": "141",
        "campus": "旗津",
        "classes": "系科",
        "name": "海事資訊科技系學會",
        "content": "",
        "facebook": "",
        "instagram": "",
        "other": ""
    },
    {
        "ord": "142",
        "campus": "旗津",
        "classes": "康樂",
        "name": "流行音樂社",
        "content": "本社團就是大家所認知的熱音社，如果大家對於組團表演或是學習樂器有興趣的話，非常歡迎加入我們流行音樂社哦～",
        "facebook": "",
        "instagram": "https://instagram.com/nkust_ruffians_987?igshid=YmMyMTA2M2Y=",
        "other": ""
    },
    {
        "ord": "143",
        "campus": "旗津",
        "classes": "康樂",
        "name": "紅桔吉他社",
        "content": "",
        "facebook": "",
        "instagram": "",
        "other": ""
    },
    {
        "ord": "144",
        "campus": "旗津",
        "classes": "服務",
        "name": "春暉社",
        "content": "",
        "facebook": "",
        "instagram": "",
        "other": ""
    },
    {
        "ord": "145",
        "campus": "旗津",
        "classes": "體能",
        "name": "桌球社",
        "content": "大家好，我們是旗津桌球社，彼此因桌球相遇，也因桌球相識，使我們凝聚在一起，每周 二、四在旗津校區體育館地下室，做自己，也做自己想做的，愛乒才會贏!",
        "facebook": "",
        "instagram": "https://instagram.com/nkust_tabletennis?igshid=YmMyMTA2M2Y=",
        "other": ""
    },
    {
        "ord": "146",
        "campus": "旗津",
        "classes": "體能",
        "name": "帆船社",
        "content": "",
        "facebook": "",
        "instagram": "",
        "other": ""
    },
    {
        "ord": "147",
        "campus": "旗津",
        "classes": "體能",
        "name": "籃球社",
        "content": "",
        "facebook": "",
        "instagram": "",
        "other": ""
    },
    {
        "ord": "148",
        "campus": "旗津",
        "classes": "體能",
        "name": "獨木舟社",
        "content": "",
        "facebook": "",
        "instagram": "",
        "other": ""
    },
    {
        "ord": "149",
        "campus": "旗津",
        "classes": "體能",
        "name": "海洋競技社",
        "content": "我們社團是以體育競技以及傳承傳統文化為主的社團，我們希望能夠將龍舟這個傳統的體育競賽一直傳承下去，傳承其中的榮譽感、責任感以及堅持不懈的精神，我們的課程內容雖然都圍繞在體能訓練和競技技巧上但我們會在這些課程中慢慢培養群體的榮譽心與責任感，只為了青春不留白",
        "facebook": "",
        "instagram": "https://instagram.com/nkustdb?igshid=YmMyMTA2M2Y=",
        "other": ""
    },
    {
        "ord": "150",
        "campus": "旗津",
        "classes": "學藝",
        "name": "船用無人機操控社",
        "content": "歡迎各位光臨無人機操控社，此社團雖是不久前成立的社團，但我們常跟建功的社團時常連動，擁有一定數量的設備，如果喜歡製作無人機的歡迎各位",
        "facebook": "https://www.facebook.com/groups/865570518175383/?ref=share",
        "instagram": "",
        "other": ""
    }
]